genericclient_base/__init__.py
genericclient_base/exceptions.py
genericclient_base/pagination.py
genericclient_base/response.py
genericclient_base/routes.py
genericclient_base/structures.py
genericclient_base/utils.py
tests/__init__.py
tests/conftest.py
tests/test_cidict.py
tests/test_client.py
tests/test_endpoint.py
tests/test_resource.py
tests/test_resourceset.py
tests/test_response.py
tests/test_routes.py
tests/test_utils.py
genericclient_base-1.4.2.dist-info/LICENSE
genericclient_base-1.4.2.dist-info/METADATA
genericclient_base-1.4.2.dist-info/WHEEL
genericclient_base-1.4.2.dist-info/top_level.txt
genericclient_base-1.4.2.dist-info/RECORD
