Metadata-Version: 2.1
Name: genericclient-base
Version: 1.4.2
Summary: UNKNOWN
Home-page: https://github.com/genericclient/genericclient-base
Author: Flavio Curella
Author-email: flavio.curella@gmail.com
License: MIT License
Platform: UNKNOWN
Classifier: Development Status :: 4 - Beta
Classifier: Environment :: Web Environment
Classifier: Intended Audience :: Developers
Classifier: Operating System :: OS Independent
Classifier: Programming Language :: Python :: 2
Classifier: Programming Language :: Python :: 3
Classifier: License :: OSI Approved :: MIT License
Requires-Dist: attrs (>=17.4.0)
